CHANGES.txt
CONTRIBUTORS.txt
MANIFEST.in
README.txt
bootstrap.py
buildout.cfg
setup.cfg
setup.py
test-4.0.x.cfg
test-4.1.x.cfg
test-4.2.x.cfg
collective/__init__.py
collective.linguafaq.egg-info/PKG-INFO
collective.linguafaq.egg-info/SOURCES.txt
collective.linguafaq.egg-info/dependency_links.txt
collective.linguafaq.egg-info/entry_points.txt
collective.linguafaq.egg-info/namespace_packages.txt
collective.linguafaq.egg-info/not-zip-safe
collective.linguafaq.egg-info/requires.txt
collective.linguafaq.egg-info/top_level.txt
collective/linguafaq/README.txt
collective/linguafaq/__init__.py
collective/linguafaq/config.py
collective/linguafaq/configure.zcml
collective/linguafaq/testing.py
collective/linguafaq/browser/__init__.py
collective/linguafaq/browser/configure.zcml
collective/linguafaq/browser/faqview.py
collective/linguafaq/browser/linktocontactform.pt
collective/linguafaq/browser/onefaqview.py
collective/linguafaq/browser/viewlets.py
collective/linguafaq/browser/javascripts/linguafaq.js
collective/linguafaq/browser/templates/all_view.pt
collective/linguafaq/browser/templates/index_view.pt
collective/linguafaq/browser/templates/onefaqview.pt
collective/linguafaq/content/__init__.py
collective/linguafaq/content/configure.zcml
collective/linguafaq/content/faqfolder.py
collective/linguafaq/content/faqgroup.py
collective/linguafaq/content/faqitem.py
collective/linguafaq/interfaces/__init__.py
collective/linguafaq/interfaces/faqfolder.py
collective/linguafaq/interfaces/faqgroup.py
collective/linguafaq/interfaces/faqitem.py
collective/linguafaq/locales/Makefile
collective/linguafaq/locales/collective.linguafaq.pot
collective/linguafaq/locales/en/LC_MESSAGES/collective.linguafaq.mo
collective/linguafaq/locales/en/LC_MESSAGES/collective.linguafaq.po
collective/linguafaq/locales/fr/LC_MESSAGES/collective.linguafaq.mo
collective/linguafaq/locales/fr/LC_MESSAGES/collective.linguafaq.po
collective/linguafaq/locales/nl/LC_MESSAGES/collective.linguafaq.mo
collective/linguafaq/locales/nl/LC_MESSAGES/collective.linguafaq.po
collective/linguafaq/locales/pt_BR/LC_MESSAGES/collective.linguafaq.mo
collective/linguafaq/locales/pt_BR/LC_MESSAGES/collective.linguafaq.po
collective/linguafaq/profiles/default/cssregistry.xml
collective/linguafaq/profiles/default/factorytool.xml
collective/linguafaq/profiles/default/jsregistry.xml
