Metadata-Version: 1.0
Name: collective.linguafaq
Version: 0.5
Summary: A simple multilanguage faq
Home-page: http://www.cirb.irisnet.be
Author: Benoit Suttor - CIRB/CIBG
Author-email: bsuttor@cirb.irisnet.be
License: GPL
Keywords: plone faq
Platform: UNKNOWN
Classifier: Development Status :: 3 - Alpha
Classifier: Environment :: Web Environment
Classifier: Framework :: Plone
Classifier: Framework :: Plone :: 4.0
Classifier: Framework :: Plone :: 4.1
Classifier: Framework :: Plone :: 4.2
Classifier: Intended Audience :: End Users/Desktop
Classifier: Intended Audience :: System Administrators
Classifier: License :: OSI Approved :: GNU General Public License (GPL)
Classifier: Operating System :: OS Independent
Classifier: Programming Language :: Python
Classifier: Topic :: Software Development :: Libraries :: Python Modules
